pyscaffold/__init__.py
pyscaffold/config.py
pyscaffold/constants.py
pyscaffold/main.py
pyscaffold/project_structure.py
pyscaffold/assets/default.json
pyscaffold/services/__init__.py
pyscaffold/services/generate_structure.py
pscaffold-0.1.7.dist-info/METADATA
pscaffold-0.1.7.dist-info/WHEEL
pscaffold-0.1.7.dist-info/entry_points.txt
pscaffold-0.1.7.dist-info/top_level.txt
pscaffold-0.1.7.dist-info/RECORD
