Metadata-Version: 2.4
Name: pscaffold
Version: 0.1.7
Summary: Add your description here
Requires-Python: >=3.11
Requires-Dist: requests>=2.32.5
Requires-Dist: typer[all]>=0.16.1
